{"urls":{"https://intefp.travail-emploi.gouv.fr/":{"status":301},"http://intefp.travail-emploi.gouv.fr/fr":{"status":301}},"technologies":[{"slug":"drupal","name":"Drupal","description":"Drupal is a free and open-source web content management framework.","confidence":100,"version":"10","icon":"Drupal.svg","website":"https://www.drupal.org/","cpe":"cpe:2.3:a:drupal:drupal:*:*:*:*:*:*:*:*","categories":[{"id":1,"slug":"cms","name":"CMS"}]},{"slug":"php","name":"PHP","description":"PHP is a general-purpose scripting language used for web development.","confidence":100,"version":null,"icon":"PHP.svg","website":"https://php.net","cpe":"cpe:2.3:a:php:php:*:*:*:*:*:*:*:*","categories":[{"id":27,"slug":"programming-languages","name":"Programming languages"}]},{"slug":"cloudflare","name":"Cloudflare","description":"Cloudflare is a web-infrastructure and website-security company, providing content-delivery-network services, DDoS mitigation, Internet security, and distributed domain-name-server services.","confidence":100,"version":null,"icon":"CloudFlare.svg","website":"https://www.cloudflare.com","cpe":null,"categories":[{"id":31,"slug":"cdn","name":"CDN"}]},{"slug":"cdnjs","name":"cdnjs","description":"cdnjs is a free distributed JS library delivery service.","confidence":100,"version":null,"icon":"cdnjs.svg","website":"https://cdnjs.com","cpe":null,"categories":[{"id":31,"slug":"cdn","name":"CDN"}]},{"slug":"matomo-analytics","name":"Matomo Analytics","description":"Matomo Analytics is a free and open-source web analytics application, that runs on a PHP/MySQL web-server.","confidence":100,"version":null,"icon":"Matomo.svg","website":"https://matomo.org","cpe":"cpe:2.3:a:matomo:matomo:*:*:*:*:*:*:*:*","categories":[{"id":10,"slug":"analytics","name":"Analytics"}]},{"slug":"jquery","name":"jQuery","description":"jQuery is a JavaScript library which is a free, open-source software designed to simplify HTML DOM tree traversal and manipulation, as well as event handling, CSS animation, and Ajax.","confidence":100,"version":"3.7.1","icon":"jQuery.svg","website":"https://jquery.com","cpe":"cpe:2.3:a:jquery:jquery:*:*:*:*:*:*:*:*","categories":[{"id":59,"slug":"javascript-libraries","name":"JavaScript libraries"}]}]}
