{
  "scan": {
    "algorithmVersion": 4,
    "grade": "D-",
    "error": null,
    "score": 25,
    "statusCode": 200,
    "testsFailed": 2,
    "testsPassed": 8,
    "testsQuantity": 10,
    "responseHeaders": {
      "server": "nginx",
      "date": "Tue, 04 Nov 2025 13:43:32 GMT",
      "content-type": "text/html; charset=utf-8",
      "transfer-encoding": "chunked",
      "connection": "close",
      "vary": "Accept-Encoding",
      "x-frame-options": "SAMEORIGIN",
      "x-xss-protection": "0",
      "x-content-type-options": "nosniff",
      "x-download-options": "noopen",
      "x-permitted-cross-domain-policies": "none",
      "referrer-policy": "strict-origin-when-cross-origin",
      "link": "</assets/application-f7a299cce4a71700e9875df98c8f61a92a8cf6abbd0a7f32408fcd7986ac47fa.css>; rel=preload; as=style; nopush,</assets/application-e93a698f6751f4ce41096942bf9061eb4fb0635452ab4d711fe56ffdc437820d.js>; rel=preload; as=script; nopush",
      "cache-control": "max-age=86400, public",
      "etag": "W/\"a3c7f5ca8b7a610ab7ae121195fcd57a\"",
      "x-request-id": "fb44d1db-70c7-4aef-ad36-3d3d0eed0900",
      "x-runtime": "0.006557",
      "strict-transport-security": "max-age=15724800; includeSubdomains"
    }
  },
  "tests": {
    "content-security-policy": {
      "expectation": "csp-implemented-with-no-unsafe",
      "pass": false,
      "result": "csp-not-implemented",
      "scoreModifier": -25,
      "data": null,
      "http": false,
      "meta": false,
      "policy": null,
      "numPolicies": 0
    },
    "cookies": {
      "expectation": "cookies-secure-with-httponly-sessions",
      "pass": true,
      "result": "cookies-not-found",
      "scoreModifier": 0,
      "data": null,
      "sameSite": false
    },
    "cross-origin-resource-sharing": {
      "expectation": "cross-origin-resource-sharing-not-implemented",
      "pass": true,
      "result": "cross-origin-resource-sharing-not-implemented",
      "scoreModifier": 0,
      "data": null
    },
    "redirection": {
      "expectation": "redirection-to-https",
      "pass": true,
      "result": "redirection-to-https",
      "scoreModifier": 0,
      "destination": "https://packages.data.code.gouv.fr/",
      "redirects": true,
      "route": [
        "http://packages.data.code.gouv.fr/",
        "https://packages.data.code.gouv.fr/"
      ],
      "statusCode": 200
    },
    "referrer-policy": {
      "expectation": "referrer-policy-private",
      "pass": true,
      "result": "referrer-policy-private",
      "scoreModifier": 5,
      "data": "strict-origin-when-cross-origin",
      "http": true,
      "meta": false
    },
    "strict-transport-security": {
      "expectation": "hsts-implemented-max-age-at-least-six-months",
      "pass": true,
      "result": "hsts-implemented-max-age-at-least-six-months",
      "scoreModifier": 0,
      "data": "max-age=15724800; includeSubdomains",
      "includeSubDomains": true,
      "maxAge": 15724800,
      "preload": false,
      "preloaded": false
    },
    "subresource-integrity": {
      "expectation": "sri-implemented-and-external-scripts-loaded-securely",
      "pass": false,
      "result": "sri-not-implemented-and-external-scripts-not-loaded-securely",
      "scoreModifier": -50,
      "data": {
        "//unpkg.com/@highlightjs/cdn-assets@11.5.1/highlight.min.js": {
          "crossorigin": null,
          "integrity": null
        }
      }
    },
    "x-content-type-options": {
      "expectation": "x-content-type-options-nosniff",
      "pass": true,
      "result": "x-content-type-options-nosniff",
      "scoreModifier": 0,
      "data": "nosniff"
    },
    "x-frame-options": {
      "expectation": "x-frame-options-sameorigin-or-deny",
      "pass": true,
      "result": "x-frame-options-sameorigin-or-deny",
      "scoreModifier": 0,
      "data": "SAMEORIGIN"
    },
    "cross-origin-resource-policy": {
      "expectation": "corp-implemented-with-same-site",
      "pass": true,
      "result": "corp-not-implemented",
      "scoreModifier": 0,
      "data": null,
      "http": false,
      "meta": false
    }
  }
}
