{
  "scan": {
    "algorithmVersion": 4,
    "grade": "C+",
    "error": null,
    "score": 60,
    "statusCode": 200,
    "testsFailed": 2,
    "testsPassed": 8,
    "testsQuantity": 10,
    "responseHeaders": {
      "date": "Mon, 03 Nov 2025 20:23:38 GMT",
      "server": "Apache/2.4.58 (Ubuntu)",
      "x-content-type-options": "nosniff",
      "cache-control": "max-age=300, public",
      "x-drupal-dynamic-cache": "MISS",
      "content-language": "fr",
      "x-frame-options": "SAMEORIGIN",
      "x-drupal-cache-tags": "block_view config:atos_dse_home.settings config:block.block.atftd_account_menu config:block.block.atftd_blockpartenaires config:block.block.atftd_breadcrumbs config:block.block.atftd_content config:block.block.atftd_help config:block.block.atftd_logosecondaire config:block.block.atftd_main_menu config:block.block.atftd_menuaccelerateurs config:block.block.atftd_messages config:block.block.atftd_page_title config:block.block.atftd_powered config:block.block.atftd_primary_admin_actions config:block.block.atftd_primary_local_tasks config:block.block.atftd_secondary_local_tasks config:block.block.atftd_selecteurdelangue config:block.block.atftd_site_branding config:block.block.atftd_syndicate config:block.block.atftd_views_block__ressources_sauvegardees_block_1 config:block.block.identitedusite config:block_list config:configurable_language_list config:dse_by_atos.settings config:filter.format.basic_html config:flag.flag.ressources_sauvegardees config:google_tag.container.GTM-PJZ6Z2T3.66587baa8f6b90.25016547 config:google_tag_container_list config:image.style.banniere_desktop_1440x440 config:image.style.banniere_mobile_480_360 config:image.style.medium_300_x_300 config:image.style.thumbnail config:image.style.xs_32_9 config:responsive_image.styles.banniere config:system.menu.main config:system.site config:user.role.anonymous error_dse.settings file:113 file:125 file:126 file:132 file:136 file:138 file:139 file:165 file:166 file:167 file:168 file:169 file:170 file:171 file:172 file:175 file:215 file:225 file:254 file:255 file:276 file:277 file:287 file:297 file:63 file:64 file:65 file:67 file:68 file:69 file:70 file:71 file:72 file:73 file:74 file:75 file:76 file:77 file:78 file:79 file:80 file:81 file:82 file:83 file:84 file:85 file:86 file:87 file:88 file:89 file:90 file:91 file:92 file:93 http_response local_task media:101 media:102 media:128 media:129 media:130 media:131 media:132 media:133 media:134 media:135 media:137 media:162 media:175 media:207 media:208 media:228 media:237 media:246 media:83 media:88 media:89 media:95 media:99 media_view menu_link_content:10 menu_link_content:11 menu_link_content:12 menu_link_content:13 menu_link_content:14 menu_link_content:15 menu_link_content:16 menu_link_content:17 menu_link_content:18 menu_link_content:19 menu_link_content:20 menu_link_content:21 menu_link_content:22 menu_link_content:23 menu_link_content:24 menu_link_content:25 menu_link_content:26 menu_link_content:27 menu_link_content:28 menu_link_content:29 menu_link_content:30 menu_link_content:31 menu_link_content:32 menu_link_content:33 menu_link_content:34 menu_link_content:35 menu_link_content:36 menu_link_content:37 menu_link_content:38 menu_link_content:39 menu_link_content:40 menu_link_content:8 menu_link_content:9 node:10 node:3 node:386 node:387 node:4 node:705 node:706 node:707 node:708 node_view rendered user:226",
      "x-drupal-cache-contexts": "cookies:big_pipe_nojs languages route session.exists theme timezone url user.permissions user.roles:authenticated",
      "x-drupal-cache-max-age": "-1 (Permanent)",
      "expires": "Sun, 19 Nov 1978 05:00:00 GMT",
      "last-modified": "Fri, 31 Oct 2025 16:03:57 GMT",
      "etag": "\"1761926637-gzip\"",
      "vary": "Cookie,Accept-Encoding",
      "x-generator": "Drupal 10 (https://www.drupal.org)",
      "content-security-policy": "object-src 'none'; frame-ancestors 'self'",
      "x-drupal-cache": "HIT",
      "connection": "close",
      "transfer-encoding": "chunked",
      "content-type": "text/html; charset=UTF-8"
    }
  },
  "tests": {
    "content-security-policy": {
      "expectation": "csp-implemented-with-no-unsafe",
      "pass": false,
      "result": "csp-implemented-with-unsafe-inline",
      "scoreModifier": -20,
      "data": {
        "object-src": [
          "'none'"
        ],
        "frame-ancestors": [
          "'self'"
        ]
      },
      "http": true,
      "meta": false,
      "policy": {
        "antiClickjacking": true,
        "defaultNone": false,
        "insecureBaseUri": true,
        "insecureFormAction": true,
        "insecureSchemeActive": false,
        "insecureSchemePassive": false,
        "strictDynamic": false,
        "unsafeEval": false,
        "unsafeInline": true,
        "unsafeInlineStyle": true,
        "unsafeObjects": false
      },
      "numPolicies": 1
    },
    "cookies": {
      "expectation": "cookies-secure-with-httponly-sessions",
      "pass": true,
      "result": "cookies-not-found",
      "scoreModifier": 0,
      "data": null,
      "sameSite": false
    },
    "cross-origin-resource-sharing": {
      "expectation": "cross-origin-resource-sharing-not-implemented",
      "pass": true,
      "result": "cross-origin-resource-sharing-not-implemented",
      "scoreModifier": 0,
      "data": null
    },
    "redirection": {
      "expectation": "redirection-to-https",
      "pass": true,
      "result": "redirection-to-https",
      "scoreModifier": 0,
      "destination": "https://www.francetourismedurable.gouv.fr/",
      "redirects": true,
      "route": [
        "http://francetourismedurable.gouv.fr/",
        "https://francetourismedurable.gouv.fr/",
        "https://www.francetourismedurable.gouv.fr/"
      ],
      "statusCode": 200
    },
    "referrer-policy": {
      "expectation": "referrer-policy-private",
      "pass": true,
      "result": "referrer-policy-not-implemented",
      "scoreModifier": 0,
      "data": null,
      "http": false,
      "meta": false
    },
    "strict-transport-security": {
      "expectation": "hsts-implemented-max-age-at-least-six-months",
      "pass": false,
      "result": "hsts-not-implemented",
      "scoreModifier": -20,
      "data": null,
      "includeSubDomains": false,
      "maxAge": null,
      "preload": false,
      "preloaded": false
    },
    "subresource-integrity": {
      "expectation": "sri-implemented-and-external-scripts-loaded-securely",
      "pass": true,
      "result": "sri-not-implemented-but-all-scripts-loaded-from-secure-origin",
      "scoreModifier": 0,
      "data": {}
    },
    "x-content-type-options": {
      "expectation": "x-content-type-options-nosniff",
      "pass": true,
      "result": "x-content-type-options-nosniff",
      "scoreModifier": 0,
      "data": "nosniff"
    },
    "x-frame-options": {
      "expectation": "x-frame-options-sameorigin-or-deny",
      "pass": true,
      "result": "x-frame-options-implemented-via-csp",
      "scoreModifier": 5,
      "data": "SAMEORIGIN"
    },
    "cross-origin-resource-policy": {
      "expectation": "corp-implemented-with-same-site",
      "pass": true,
      "result": "corp-not-implemented",
      "scoreModifier": 0,
      "data": null,
      "http": false,
      "meta": false
    }
  }
}
