{
  "links": [
    {
      "url": {
        "protocol": "https:",
        "slashes": true,
        "auth": null,
        "host": "mediatheque-sga.defense.gouv.fr",
        "port": null,
        "hostname": "mediatheque-sga.defense.gouv.fr",
        "hash": null,
        "search": null,
        "query": null,
        "pathname": "/",
        "path": "/",
        "href": "https://mediatheque-sga.defense.gouv.fr/"
      },
      "link": "https://mediatheque-sga.defense.gouv.fr/",
      "line": "--2025-11-04 07:13:46--  https://mediatheque-sga.defense.gouv.fr/",
      "broken": false
    },
    {
      "url": {
        "protocol": "https:",
        "slashes": true,
        "auth": null,
        "host": "mediatheque-sga.defense.gouv.fr",
        "port": null,
        "hostname": "mediatheque-sga.defense.gouv.fr",
        "hash": null,
        "search": null,
        "query": null,
        "pathname": "/robots.txt",
        "path": "/robots.txt",
        "href": "https://mediatheque-sga.defense.gouv.fr/robots.txt"
      },
      "link": "https://mediatheque-sga.defense.gouv.fr/robots.txt",
      "line": "--2025-11-04 07:13:47--  https://mediatheque-sga.defense.gouv.fr/robots.txt",
      "broken": false
    },
    {
      "url": {
        "protocol": "https:",
        "slashes": true,
        "auth": null,
        "host": "mediatheque-sga.defense.gouv.fr",
        "port": null,
        "hostname": "mediatheque-sga.defense.gouv.fr",
        "hash": null,
        "search": null,
        "query": null,
        "pathname": "/home/favicon.ico",
        "path": "/home/favicon.ico",
        "href": "https://mediatheque-sga.defense.gouv.fr/home/favicon.ico"
      },
      "link": "https://mediatheque-sga.defense.gouv.fr/home/favicon.ico",
      "line": "--2025-11-04 07:13:47--  https://mediatheque-sga.defense.gouv.fr/home/favicon.ico",
      "broken": false
    },
    {
      "url": {
        "protocol": "https:",
        "slashes": true,
        "auth": null,
        "host": "mediatheque-sga.defense.gouv.fr",
        "port": null,
        "hostname": "mediatheque-sga.defense.gouv.fr",
        "hash": null,
        "search": null,
        "query": null,
        "pathname": "/home/style.css",
        "path": "/home/style.css",
        "href": "https://mediatheque-sga.defense.gouv.fr/home/style.css"
      },
      "link": "https://mediatheque-sga.defense.gouv.fr/home/style.css",
      "line": "--2025-11-04 07:13:47--  https://mediatheque-sga.defense.gouv.fr/home/style.css",
      "broken": false
    },
    {
      "url": {
        "protocol": "https:",
        "slashes": true,
        "auth": null,
        "host": "mediatheque-sga.defense.gouv.fr",
        "port": null,
        "hostname": "mediatheque-sga.defense.gouv.fr",
        "hash": null,
        "search": null,
        "query": null,
        "pathname": "/home/jquery/jquery-3.4.1.js",
        "path": "/home/jquery/jquery-3.4.1.js",
        "href": "https://mediatheque-sga.defense.gouv.fr/home/jquery/jquery-3.4.1.js"
      },
      "link": "https://mediatheque-sga.defense.gouv.fr/home/jquery/jquery-3.4.1.js",
      "line": "--2025-11-04 07:13:48--  https://mediatheque-sga.defense.gouv.fr/home/jquery/jquery-3.4.1.js",
      "broken": false
    },
    {
      "url": {
        "protocol": "https:",
        "slashes": true,
        "auth": null,
        "host": "mediatheque-sga.defense.gouv.fr",
        "port": null,
        "hostname": "mediatheque-sga.defense.gouv.fr",
        "hash": null,
        "search": null,
        "query": null,
        "pathname": "/SGA-COM/scripts/ajaris.websuite.publicdoclist.2.0.js",
        "path": "/SGA-COM/scripts/ajaris.websuite.publicdoclist.2.0.js",
        "href": "https://mediatheque-sga.defense.gouv.fr/SGA-COM/scripts/ajaris.websuite.publicdoclist.2.0.js"
      },
      "link": "https://mediatheque-sga.defense.gouv.fr/SGA-COM/scripts/ajaris.websuite.publicdoclist.2.0.js",
      "line": "--2025-11-04 07:13:48--  https://mediatheque-sga.defense.gouv.fr/SGA-COM/scripts/ajaris.websuite.publicdoclist.2.0.js",
      "broken": false
    },
    {
      "url": {
        "protocol": "https:",
        "slashes": true,
        "auth": null,
        "host": "mediatheque-sga.defense.gouv.fr",
        "port": null,
        "hostname": "mediatheque-sga.defense.gouv.fr",
        "hash": null,
        "search": null,
        "query": null,
        "pathname": "/home/images/MIN_Armees_RVB.svg",
        "path": "/home/images/MIN_Armees_RVB.svg",
        "href": "https://mediatheque-sga.defense.gouv.fr/home/images/MIN_Armees_RVB.svg"
      },
      "link": "https://mediatheque-sga.defense.gouv.fr/home/images/MIN_Armees_RVB.svg",
      "line": "--2025-11-04 07:13:48--  https://mediatheque-sga.defense.gouv.fr/home/images/MIN_Armees_RVB.svg",
      "broken": false
    },
    {
      "url": {
        "protocol": "https:",
        "slashes": true,
        "auth": null,
        "host": "mediatheque-sga.defense.gouv.fr",
        "port": null,
        "hostname": "mediatheque-sga.defense.gouv.fr",
        "hash": null,
        "search": null,
        "query": null,
        "pathname": "/home/Typo/Marianne-Light.otf",
        "path": "/home/Typo/Marianne-Light.otf",
        "href": "https://mediatheque-sga.defense.gouv.fr/home/Typo/Marianne-Light.otf"
      },
      "link": "https://mediatheque-sga.defense.gouv.fr/home/Typo/Marianne-Light.otf",
      "line": "--2025-11-04 07:13:48--  https://mediatheque-sga.defense.gouv.fr/home/Typo/Marianne-Light.otf",
      "broken": false
    },
    {
      "url": {
        "protocol": "https:",
        "slashes": true,
        "auth": null,
        "host": "mediatheque-sga.defense.gouv.fr",
        "port": null,
        "hostname": "mediatheque-sga.defense.gouv.fr",
        "hash": null,
        "search": null,
        "query": null,
        "pathname": "/home/Typo/Marianne-Regular.otf",
        "path": "/home/Typo/Marianne-Regular.otf",
        "href": "https://mediatheque-sga.defense.gouv.fr/home/Typo/Marianne-Regular.otf"
      },
      "link": "https://mediatheque-sga.defense.gouv.fr/home/Typo/Marianne-Regular.otf",
      "line": "--2025-11-04 07:13:48--  https://mediatheque-sga.defense.gouv.fr/home/Typo/Marianne-Regular.otf",
      "broken": false
    }
  ],
  "broken": []
}