{"urls":{"https://www.telepac.agriculture.gouv.fr/":{"status":301},"https://www.telepac.agriculture.gouv.fr/telepac/auth/accueil.action":{"status":200}},"technologies":[{"slug":"java","name":"Java","description":"Java is a class-based, object-oriented programming language that is designed to have as few implementation dependencies as possible.","confidence":100,"version":null,"icon":"Java.svg","website":"https://java.com","cpe":"cpe:2.3:a:oracle:jre:*:*:*:*:*:*:*:*","categories":[{"id":27,"slug":"programming-languages","name":"Programming languages"}]},{"slug":"apache-http-server","name":"Apache HTTP Server","description":"Apache is a free and open-source cross-platform web server software.","confidence":100,"version":null,"icon":"Apache.svg","website":"https://httpd.apache.org/","cpe":"cpe:2.3:a:apache:http_server:*:*:*:*:*:*:*:*","categories":[{"id":22,"slug":"web-servers","name":"Web servers"}]},{"slug":"mailjet","name":"Mailjet","description":"Mailjet is an email delivery service for marketing and developer teams.","confidence":100,"version":null,"icon":"Mailjet.svg","website":"https://www.mailjet.com/","cpe":null,"categories":[{"id":75,"slug":"email","name":"Email"}],"rootPath":true},{"slug":"jquery","name":"jQuery","description":"jQuery is a JavaScript library which is a free, open-source software designed to simplify HTML DOM tree traversal and manipulation, as well as event handling, CSS animation, and Ajax.","confidence":100,"version":"1.4.4","icon":"jQuery.svg","website":"https://jquery.com","cpe":"cpe:2.3:a:jquery:jquery:*:*:*:*:*:*:*:*","categories":[{"id":59,"slug":"javascript-libraries","name":"JavaScript libraries"}]},{"slug":"hsts","name":"HSTS","description":"HTTP Strict Transport Security (HSTS) informs browsers that the site should only be accessed using HTTPS.","confidence":100,"version":null,"icon":"default.svg","website":"https://www.rfc-editor.org/rfc/rfc6797#section-6.1","cpe":null,"categories":[{"id":16,"slug":"security","name":"Security"}]}]}
