{
  "links": [
    {
      "url": {
        "protocol": "https:",
        "slashes": true,
        "auth": null,
        "host": "pjm.social.gouv.fr",
        "port": null,
        "hostname": "pjm.social.gouv.fr",
        "hash": null,
        "search": null,
        "query": null,
        "pathname": "/",
        "path": "/",
        "href": "https://pjm.social.gouv.fr/"
      },
      "link": "https://pjm.social.gouv.fr/",
      "line": "--2025-11-04 14:53:05--  https://pjm.social.gouv.fr/",
      "broken": false
    },
    {
      "url": {
        "protocol": "https:",
        "slashes": true,
        "auth": null,
        "host": "pjm.social.gouv.fr",
        "port": null,
        "hostname": "pjm.social.gouv.fr",
        "hash": null,
        "search": null,
        "query": null,
        "pathname": "/index.html",
        "path": "/index.html",
        "href": "https://pjm.social.gouv.fr/index.html"
      },
      "link": "https://pjm.social.gouv.fr/index.html",
      "line": "--2025-11-04 14:53:05--  https://pjm.social.gouv.fr/index.html",
      "broken": false
    },
    {
      "url": {
        "protocol": "https:",
        "slashes": true,
        "auth": null,
        "host": "pjm.social.gouv.fr",
        "port": null,
        "hostname": "pjm.social.gouv.fr",
        "hash": null,
        "search": null,
        "query": null,
        "pathname": "/robots.txt",
        "path": "/robots.txt",
        "href": "https://pjm.social.gouv.fr/robots.txt"
      },
      "link": "https://pjm.social.gouv.fr/robots.txt",
      "line": "--2025-11-04 14:53:06--  https://pjm.social.gouv.fr/robots.txt",
      "broken": false
    },
    {
      "url": {
        "protocol": "https:",
        "slashes": true,
        "auth": null,
        "host": "pjm.social.gouv.fr",
        "port": null,
        "hostname": "pjm.social.gouv.fr",
        "hash": null,
        "search": null,
        "query": null,
        "pathname": "/favicon.ico",
        "path": "/favicon.ico",
        "href": "https://pjm.social.gouv.fr/favicon.ico"
      },
      "link": "https://pjm.social.gouv.fr/favicon.ico",
      "line": "--2025-11-04 14:53:06--  https://pjm.social.gouv.fr/favicon.ico",
      "broken": false
    },
    {
      "url": {
        "protocol": "https:",
        "slashes": true,
        "auth": null,
        "host": "pjm.social.gouv.fr",
        "port": null,
        "hostname": "pjm.social.gouv.fr",
        "hash": null,
        "search": null,
        "query": null,
        "pathname": "/bg-index.jpg",
        "path": "/bg-index.jpg",
        "href": "https://pjm.social.gouv.fr/bg-index.jpg"
      },
      "link": "https://pjm.social.gouv.fr/bg-index.jpg",
      "line": "--2025-11-04 14:53:06--  https://pjm.social.gouv.fr/bg-index.jpg",
      "broken": false
    },
    {
      "url": {
        "protocol": "https:",
        "slashes": true,
        "auth": null,
        "host": "pjm.social.gouv.fr",
        "port": null,
        "hostname": "pjm.social.gouv.fr",
        "hash": null,
        "search": null,
        "query": null,
        "pathname": "/logo_ministere.png",
        "path": "/logo_ministere.png",
        "href": "https://pjm.social.gouv.fr/logo_ministere.png"
      },
      "link": "https://pjm.social.gouv.fr/logo_ministere.png",
      "line": "--2025-11-04 14:53:06--  https://pjm.social.gouv.fr/logo_ministere.png",
      "broken": false
    }
  ],
  "broken": []
}