{
  "scan": {
    "algorithmVersion": 4,
    "grade": "C+",
    "error": null,
    "score": 60,
    "statusCode": 200,
    "testsFailed": 2,
    "testsPassed": 8,
    "testsQuantity": 10,
    "responseHeaders": {
      "date": "Wed, 05 Nov 2025 03:46:35 GMT",
      "content-type": "text/html; charset=UTF-8",
      "content-length": "11553",
      "connection": "close",
      "cache-control": "no-store, no-cache, must-revalidate, post-check=0, pre-check=0",
      "set-cookie": [
        "SESSID=4cff24b7-360a-497a-aa2c-746550a6fdae; Path=/; SameSite=Lax; HttpOnly; Secure"
      ],
      "x-frame-options": "DENY",
      "strict-transport-security": "max-age=31536000;",
      "x-xss-protection": "1; mode=block",
      "x-content-type-options": "nosniff",
      "content-security-policy": "default-src 'self'; script-src 'self' 'unsafe-inline'; img-src * data:; style-src 'self' 'unsafe-inline'; frame-ancestors 'none';"
    }
  },
  "tests": {
    "content-security-policy": {
      "expectation": "csp-implemented-with-no-unsafe",
      "pass": false,
      "result": "csp-implemented-with-unsafe-inline",
      "scoreModifier": -20,
      "data": {
        "default-src": [
          "'self'"
        ],
        "script-src": [
          "'self'",
          "'unsafe-inline'"
        ],
        "img-src": [
          "*",
          "data:"
        ],
        "style-src": [
          "'self'",
          "'unsafe-inline'"
        ],
        "frame-ancestors": [
          "'none'"
        ]
      },
      "http": true,
      "meta": false,
      "policy": {
        "antiClickjacking": true,
        "defaultNone": false,
        "insecureBaseUri": true,
        "insecureFormAction": true,
        "insecureSchemeActive": false,
        "insecureSchemePassive": false,
        "strictDynamic": false,
        "unsafeEval": false,
        "unsafeInline": true,
        "unsafeInlineStyle": true,
        "unsafeObjects": false
      },
      "numPolicies": 1
    },
    "cookies": {
      "expectation": "cookies-secure-with-httponly-sessions",
      "pass": true,
      "result": "cookies-secure-with-httponly-sessions-and-samesite",
      "scoreModifier": 5,
      "data": {
        "SESSID": {
          "domain": "vpn.cabinet.developpement-durable.gouv.fr",
          "httponly": true,
          "path": "/",
          "port": null,
          "samesite": "lax",
          "secure": true
        }
      },
      "sameSite": true
    },
    "cross-origin-resource-sharing": {
      "expectation": "cross-origin-resource-sharing-not-implemented",
      "pass": true,
      "result": "cross-origin-resource-sharing-not-implemented",
      "scoreModifier": 0,
      "data": null
    },
    "redirection": {
      "expectation": "redirection-to-https",
      "pass": false,
      "result": "redirection-missing",
      "scoreModifier": -20,
      "destination": "http://vpn.cabinet.developpement-durable.gouv.fr/",
      "redirects": false,
      "route": [
        "http://vpn.cabinet.developpement-durable.gouv.fr/"
      ],
      "statusCode": 403
    },
    "referrer-policy": {
      "expectation": "referrer-policy-private",
      "pass": true,
      "result": "referrer-policy-not-implemented",
      "scoreModifier": 0,
      "data": null,
      "http": false,
      "meta": false
    },
    "strict-transport-security": {
      "expectation": "hsts-implemented-max-age-at-least-six-months",
      "pass": true,
      "result": "hsts-implemented-max-age-at-least-six-months",
      "scoreModifier": 0,
      "data": "max-age=31536000;",
      "includeSubDomains": false,
      "maxAge": 31536000,
      "preload": false,
      "preloaded": false
    },
    "subresource-integrity": {
      "expectation": "sri-implemented-and-external-scripts-loaded-securely",
      "pass": true,
      "result": "sri-not-implemented-but-all-scripts-loaded-from-secure-origin",
      "scoreModifier": 0,
      "data": {}
    },
    "x-content-type-options": {
      "expectation": "x-content-type-options-nosniff",
      "pass": true,
      "result": "x-content-type-options-nosniff",
      "scoreModifier": 0,
      "data": "nosniff"
    },
    "x-frame-options": {
      "expectation": "x-frame-options-sameorigin-or-deny",
      "pass": true,
      "result": "x-frame-options-implemented-via-csp",
      "scoreModifier": 5,
      "data": "DENY"
    },
    "cross-origin-resource-policy": {
      "expectation": "corp-implemented-with-same-site",
      "pass": true,
      "result": "corp-not-implemented",
      "scoreModifier": 0,
      "data": null,
      "http": false,
      "meta": false
    }
  }
}
