{
  "links": [
    {
      "url": {
        "protocol": "https:",
        "slashes": true,
        "auth": null,
        "host": "cybermois24.cybermalveillance.gouv.fr",
        "port": null,
        "hostname": "cybermois24.cybermalveillance.gouv.fr",
        "hash": null,
        "search": null,
        "query": null,
        "pathname": "/",
        "path": "/",
        "href": "https://cybermois24.cybermalveillance.gouv.fr/"
      },
      "link": "https://cybermois24.cybermalveillance.gouv.fr/",
      "line": "--2025-10-31 04:39:45--  https://cybermois24.cybermalveillance.gouv.fr/",
      "broken": false
    },
    {
      "url": {
        "protocol": "https:",
        "slashes": true,
        "auth": null,
        "host": "cybermois24.cybermalveillance.gouv.fr",
        "port": null,
        "hostname": "cybermois24.cybermalveillance.gouv.fr",
        "hash": null,
        "search": null,
        "query": null,
        "pathname": "/robots.txt",
        "path": "/robots.txt",
        "href": "https://cybermois24.cybermalveillance.gouv.fr/robots.txt"
      },
      "link": "https://cybermois24.cybermalveillance.gouv.fr/robots.txt",
      "line": "--2025-10-31 04:39:45--  https://cybermois24.cybermalveillance.gouv.fr/robots.txt",
      "broken": false
    },
    {
      "url": {
        "protocol": "https:",
        "slashes": true,
        "auth": null,
        "host": "cybermois24.cybermalveillance.gouv.fr",
        "port": null,
        "hostname": "cybermois24.cybermalveillance.gouv.fr",
        "hash": null,
        "search": null,
        "query": null,
        "pathname": "/assets/index-CvKdD0b0.js",
        "path": "/assets/index-CvKdD0b0.js",
        "href": "https://cybermois24.cybermalveillance.gouv.fr/assets/index-CvKdD0b0.js"
      },
      "link": "https://cybermois24.cybermalveillance.gouv.fr/assets/index-CvKdD0b0.js",
      "line": "--2025-10-31 04:39:46--  https://cybermois24.cybermalveillance.gouv.fr/assets/index-CvKdD0b0.js",
      "broken": false
    },
    {
      "url": {
        "protocol": "https:",
        "slashes": true,
        "auth": null,
        "host": "cybermois24.cybermalveillance.gouv.fr",
        "port": null,
        "hostname": "cybermois24.cybermalveillance.gouv.fr",
        "hash": null,
        "search": null,
        "query": null,
        "pathname": "/assets/index-DXKN12uG.css",
        "path": "/assets/index-DXKN12uG.css",
        "href": "https://cybermois24.cybermalveillance.gouv.fr/assets/index-DXKN12uG.css"
      },
      "link": "https://cybermois24.cybermalveillance.gouv.fr/assets/index-DXKN12uG.css",
      "line": "--2025-10-31 04:39:46--  https://cybermois24.cybermalveillance.gouv.fr/assets/index-DXKN12uG.css",
      "broken": false
    },
    {
      "url": {
        "protocol": "https:",
        "slashes": true,
        "auth": null,
        "host": "cybermois24.cybermalveillance.gouv.fr",
        "port": null,
        "hostname": "cybermois24.cybermalveillance.gouv.fr",
        "hash": null,
        "search": "?t=1734404658139",
        "query": "t=1734404658139",
        "pathname": "/assets/remixicon-BVJ9S1ev.eot",
        "path": "/assets/remixicon-BVJ9S1ev.eot?t=1734404658139",
        "href": "https://cybermois24.cybermalveillance.gouv.fr/assets/remixicon-BVJ9S1ev.eot?t=1734404658139"
      },
      "link": "https://cybermois24.cybermalveillance.gouv.fr/assets/remixicon-BVJ9S1ev.eot?t=1734404658139",
      "line": "--2025-10-31 04:39:46--  https://cybermois24.cybermalveillance.gouv.fr/assets/remixicon-BVJ9S1ev.eot?t=1734404658139",
      "broken": false
    },
    {
      "url": {
        "protocol": "https:",
        "slashes": true,
        "auth": null,
        "host": "cybermois24.cybermalveillance.gouv.fr",
        "port": null,
        "hostname": "cybermois24.cybermalveillance.gouv.fr",
        "hash": null,
        "search": "?t=1734404658139",
        "query": "t=1734404658139",
        "pathname": "/assets/remixicon-BVvFtaex.woff2",
        "path": "/assets/remixicon-BVvFtaex.woff2?t=1734404658139",
        "href": "https://cybermois24.cybermalveillance.gouv.fr/assets/remixicon-BVvFtaex.woff2?t=1734404658139"
      },
      "link": "https://cybermois24.cybermalveillance.gouv.fr/assets/remixicon-BVvFtaex.woff2?t=1734404658139",
      "line": "--2025-10-31 04:39:46--  https://cybermois24.cybermalveillance.gouv.fr/assets/remixicon-BVvFtaex.woff2?t=1734404658139",
      "broken": false
    },
    {
      "url": {
        "protocol": "https:",
        "slashes": true,
        "auth": null,
        "host": "cybermois24.cybermalveillance.gouv.fr",
        "port": null,
        "hostname": "cybermois24.cybermalveillance.gouv.fr",
        "hash": null,
        "search": "?t=1734404658139",
        "query": "t=1734404658139",
        "pathname": "/assets/remixicon-BBpe-Xu7.woff",
        "path": "/assets/remixicon-BBpe-Xu7.woff?t=1734404658139",
        "href": "https://cybermois24.cybermalveillance.gouv.fr/assets/remixicon-BBpe-Xu7.woff?t=1734404658139"
      },
      "link": "https://cybermois24.cybermalveillance.gouv.fr/assets/remixicon-BBpe-Xu7.woff?t=1734404658139",
      "line": "--2025-10-31 04:39:46--  https://cybermois24.cybermalveillance.gouv.fr/assets/remixicon-BBpe-Xu7.woff?t=1734404658139",
      "broken": false
    },
    {
      "url": {
        "protocol": "https:",
        "slashes": true,
        "auth": null,
        "host": "cybermois24.cybermalveillance.gouv.fr",
        "port": null,
        "hostname": "cybermois24.cybermalveillance.gouv.fr",
        "hash": null,
        "search": "?t=1734404658139",
        "query": "t=1734404658139",
        "pathname": "/assets/remixicon-CfJD46dY.ttf",
        "path": "/assets/remixicon-CfJD46dY.ttf?t=1734404658139",
        "href": "https://cybermois24.cybermalveillance.gouv.fr/assets/remixicon-CfJD46dY.ttf?t=1734404658139"
      },
      "link": "https://cybermois24.cybermalveillance.gouv.fr/assets/remixicon-CfJD46dY.ttf?t=1734404658139",
      "line": "--2025-10-31 04:39:47--  https://cybermois24.cybermalveillance.gouv.fr/assets/remixicon-CfJD46dY.ttf?t=1734404658139",
      "broken": false
    },
    {
      "url": {
        "protocol": "https:",
        "slashes": true,
        "auth": null,
        "host": "cybermois24.cybermalveillance.gouv.fr",
        "port": null,
        "hostname": "cybermois24.cybermalveillance.gouv.fr",
        "hash": null,
        "search": "?t=1734404658139",
        "query": "t=1734404658139",
        "pathname": "/assets/remixicon-C2wQ2gtc.svg",
        "path": "/assets/remixicon-C2wQ2gtc.svg?t=1734404658139",
        "href": "https://cybermois24.cybermalveillance.gouv.fr/assets/remixicon-C2wQ2gtc.svg?t=1734404658139"
      },
      "link": "https://cybermois24.cybermalveillance.gouv.fr/assets/remixicon-C2wQ2gtc.svg?t=1734404658139",
      "line": "--2025-10-31 04:39:47--  https://cybermois24.cybermalveillance.gouv.fr/assets/remixicon-C2wQ2gtc.svg?t=1734404658139",
      "broken": false
    }
  ],
  "broken": []
}