{
  "links": [
    {
      "url": {
        "protocol": "https:",
        "slashes": true,
        "auth": null,
        "host": "suivi.dalo-daho-idf.developpement-durable.gouv.fr",
        "port": null,
        "hostname": "suivi.dalo-daho-idf.developpement-durable.gouv.fr",
        "hash": null,
        "search": null,
        "query": null,
        "pathname": "/",
        "path": "/",
        "href": "https://suivi.dalo-daho-idf.developpement-durable.gouv.fr/"
      },
      "link": "https://suivi.dalo-daho-idf.developpement-durable.gouv.fr/",
      "line": "--2025-11-04 20:24:04--  https://suivi.dalo-daho-idf.developpement-durable.gouv.fr/",
      "broken": false
    },
    {
      "url": {
        "protocol": "https:",
        "slashes": true,
        "auth": null,
        "host": "suivi.dalo-daho-idf.developpement-durable.gouv.fr",
        "port": null,
        "hostname": "suivi.dalo-daho-idf.developpement-durable.gouv.fr",
        "hash": null,
        "search": null,
        "query": null,
        "pathname": "/robots.txt",
        "path": "/robots.txt",
        "href": "https://suivi.dalo-daho-idf.developpement-durable.gouv.fr/robots.txt"
      },
      "link": "https://suivi.dalo-daho-idf.developpement-durable.gouv.fr/robots.txt",
      "line": "--2025-11-04 20:24:06--  https://suivi.dalo-daho-idf.developpement-durable.gouv.fr/robots.txt",
      "broken": false
    }
  ],
  "broken": []
}