{
  "scan": {
    "algorithmVersion": 4,
    "grade": "F",
    "error": null,
    "score": 0,
    "statusCode": 200,
    "testsFailed": 4,
    "testsPassed": 6,
    "testsQuantity": 10,
    "responseHeaders": {
      "date": "Fri, 12 Sep 2025 04:08:05 GMT",
      "content-type": "text/html; charset=utf-8",
      "transfer-encoding": "chunked",
      "connection": "close",
      "cf-ray": "97dc8aa71aeee7d7-DFW",
      "x-sorting-hat-podid": "340",
      "x-sorting-hat-shopid": "66048983279",
      "x-storefront-renderer-rendered": "1",
      "set-cookie": [
        "localization=FR; path=/; expires=Sat, 12 Sep 2026 04:08:05 GMT; SameSite=Lax",
        "cart_currency=EUR; path=/; expires=Fri, 26 Sep 2025 04:08:05 GMT; SameSite=Lax",
        "_shopify_y=98b5161a-3616-40f7-8a65-acdddc53fc90; domain=marinenationale.gouv.fr; path=/; expires=Sat, 12 Sep 2026 10:08:05 GMT; SameSite=Lax",
        "_shopify_s=8e70f1a2-7d76-401b-b9ac-5b2ac3c5662b; domain=marinenationale.gouv.fr; path=/; expires=Fri, 12 Sep 2025 04:38:05 GMT; SameSite=Lax",
        "_tracking_consent=3.AMPS_USWY_f_f_fJKU4w*QRDWzGGWOBjFLtQ; domain=marinenationale.gouv.fr; path=/; expires=Sat, 12 Sep 2026 10:08:05 GMT; SameSite=Lax",
        "_orig_referrer=; domain=marinenationale.gouv.fr; path=/; expires=Fri, 26 Sep 2025 04:08:05 GMT; HttpOnly; SameSite=Lax",
        "_landing_page=%2F; domain=marinenationale.gouv.fr; path=/; expires=Fri, 26 Sep 2025 04:08:05 GMT; HttpOnly; SameSite=Lax",
        "_shopify_essential=:AZk8G-SwAAEAxbVCRc-XvLQ96ooahD0P6rH_4FZ0RFDqd53a6YtLyrONS9zvcqua0zr6Nsn3poMhvNwaAnF27q65CT44h8y5aUDNR244vBTHYoOFAx0xoi7Q05K5-2Hb_SCNG-EpJDZDNnEjYiHePWZmMSM_UreiVDBo:; Max-Age=31536000; Path=/; HttpOnly; Secure; Priority=High; SameSite=Lax"
      ],
      "link": "<https://cdn.shopify.com>; rel=\"preconnect\", <https://cdn.shopify.com>; rel=\"preconnect\"; crossorigin, <//boutique.marinenationale.gouv.fr/cdn/shop/t/26/assets/theme.css?v=14069087290360216561750774552>; as=\"style\"; rel=\"preload\", <//boutique.marinenationale.gouv.fr/cdn/shop/t/26/assets/mn.css?v=89526103147581762531750774545>; as=\"style\"; rel=\"preload\"",
      "etag": "\"cacheable:6880a541c2d5fdc36f5d04487ae3a1af\"",
      "shopify-complexity-score": "0",
      "x-frame-options": "DENY",
      "content-security-policy": "block-all-mixed-content; frame-ancestors 'none'; upgrade-insecure-requests;",
      "strict-transport-security": "max-age=7889238",
      "x-shopid": "66048983279",
      "x-shardid": "340",
      "vary": "Accept, accept-encoding",
      "content-language": "fr-FR",
      "powered-by": "Shopify",
      "server-timing": "processing;dur=393;desc=\"gc:10\", db;dur=124, db_async;dur=8.533, render;dur=247, asn;desc=\"8075\", edge;desc=\"DFW\", country;desc=\"US\", theme;desc=\"182602137941\", pageType;desc=\"index\", servedBy;desc=\"f6kz\", requestID;desc=\"b2e493a5-a505-4ab4-9c0e-7dd1b89beb8f-1757650084\", _y;desc=\"98b5161a-3616-40f7-8a65-acdddc53fc90\", _s;desc=\"8e70f1a2-7d76-401b-b9ac-5b2ac3c5662b\", _cmp;desc=\"3.AMPS_USWY_f_f_fJKU4w*QRDWzGGWOBjFLtQ\", cfRequestDuration;dur=476.000071",
      "x-dc": "gcp-us-central1,gcp-us-east1,gcp-us-east1",
      "x-request-id": "b2e493a5-a505-4ab4-9c0e-7dd1b89beb8f-1757650084",
      "alt-svc": "h3=\":443\"; ma=86400",
      "cf-cache-status": "DYNAMIC",
      "report-to": "{\"endpoints\":[{\"url\":\"https:\\/\\/a.nel.cloudflare.com\\/report\\/v4?s=EcTLm0JPfu8Nd6RFcWA6iXytxJJ4JXtrBgBrxT5pMdzNJT6zIK9E%2BTrxOhYc9X2CdDDXFDLDHOQgy8xI%2F8wNeUZNYGtvKWCbohmgp8sAjdyqNzyddILPHRsQu5bFpAvGUD3M4ZKg1WkSuT6P3DAnUiIh\"}],\"group\":\"cf-nel\",\"max_age\":604800}",
      "nel": "{\"success_fraction\":0.01,\"report_to\":\"cf-nel\",\"max_age\":604800}",
      "x-xss-protection": "1; mode=block",
      "x-content-type-options": "nosniff",
      "x-permitted-cross-domain-policies": "none",
      "x-download-options": "noopen",
      "server": "cloudflare"
    }
  },
  "tests": {
    "content-security-policy": {
      "expectation": "csp-implemented-with-no-unsafe",
      "pass": false,
      "result": "csp-implemented-with-unsafe-inline",
      "scoreModifier": -20,
      "data": {
        "block-all-mixed-content": [
          "'none'"
        ],
        "frame-ancestors": [
          "'none'"
        ],
        "upgrade-insecure-requests": [
          "'none'"
        ],
        "script-src": [
          "'none'"
        ]
      },
      "http": true,
      "meta": true,
      "policy": {
        "antiClickjacking": true,
        "defaultNone": false,
        "insecureBaseUri": true,
        "insecureFormAction": true,
        "insecureSchemeActive": false,
        "insecureSchemePassive": false,
        "strictDynamic": false,
        "unsafeEval": false,
        "unsafeInline": true,
        "unsafeInlineStyle": true,
        "unsafeObjects": true
      },
      "numPolicies": 2
    },
    "cookies": {
      "expectation": "cookies-secure-with-httponly-sessions",
      "pass": false,
      "result": "cookies-without-secure-flag",
      "scoreModifier": -20,
      "data": {
        "localization": {
          "domain": "boutique.marinenationale.gouv.fr",
          "expires": "2026-09-12T04:08:05.000Z",
          "path": "/",
          "port": null,
          "samesite": "lax"
        },
        "cart_currency": {
          "domain": "boutique.marinenationale.gouv.fr",
          "expires": "2025-09-26T04:08:05.000Z",
          "path": "/",
          "port": null,
          "samesite": "lax"
        },
        "_shopify_y": {
          "domain": "marinenationale.gouv.fr",
          "expires": "2026-09-12T10:08:05.000Z",
          "path": "/",
          "port": null,
          "samesite": "lax"
        },
        "_shopify_s": {
          "domain": "marinenationale.gouv.fr",
          "expires": "2025-09-12T04:38:05.000Z",
          "path": "/",
          "port": null,
          "samesite": "lax"
        },
        "_tracking_consent": {
          "domain": "marinenationale.gouv.fr",
          "expires": "2026-09-12T10:08:05.000Z",
          "path": "/",
          "port": null,
          "samesite": "lax"
        },
        "_orig_referrer": {
          "domain": "marinenationale.gouv.fr",
          "expires": "2025-09-26T04:08:05.000Z",
          "httponly": true,
          "path": "/",
          "port": null,
          "samesite": "lax"
        },
        "_landing_page": {
          "domain": "marinenationale.gouv.fr",
          "expires": "2025-09-26T04:08:05.000Z",
          "httponly": true,
          "path": "/",
          "port": null,
          "samesite": "lax"
        },
        "_shopify_essential": {
          "domain": "boutique.marinenationale.gouv.fr",
          "httponly": true,
          "max-age": 31536000,
          "path": "/",
          "port": null,
          "samesite": "lax",
          "secure": true
        }
      },
      "sameSite": false
    },
    "cross-origin-resource-sharing": {
      "expectation": "cross-origin-resource-sharing-not-implemented",
      "pass": true,
      "result": "cross-origin-resource-sharing-not-implemented",
      "scoreModifier": 0,
      "data": null
    },
    "redirection": {
      "expectation": "redirection-to-https",
      "pass": true,
      "result": "redirection-to-https",
      "scoreModifier": 0,
      "destination": "https://boutique.marinenationale.gouv.fr/",
      "redirects": true,
      "route": [
        "http://boutique.marinenationale.gouv.fr/",
        "https://boutique.marinenationale.gouv.fr/"
      ],
      "statusCode": 200
    },
    "referrer-policy": {
      "expectation": "referrer-policy-private",
      "pass": true,
      "result": "referrer-policy-not-implemented",
      "scoreModifier": 0,
      "data": null,
      "http": false,
      "meta": false
    },
    "strict-transport-security": {
      "expectation": "hsts-implemented-max-age-at-least-six-months",
      "pass": false,
      "result": "hsts-implemented-max-age-less-than-six-months",
      "scoreModifier": -10,
      "data": "max-age=7889238",
      "includeSubDomains": false,
      "maxAge": 7889238,
      "preload": false,
      "preloaded": false
    },
    "subresource-integrity": {
      "expectation": "sri-implemented-and-external-scripts-loaded-securely",
      "pass": false,
      "result": "sri-not-implemented-and-external-scripts-not-loaded-securely",
      "scoreModifier": -50,
      "data": {
        "//boutique.marinenationale.gouv.fr/cdn/shop/t/26/assets/es-module-shims.min.js?v=93572372115946385171750774547": {
          "crossorigin": null,
          "integrity": null
        },
        "//boutique.marinenationale.gouv.fr/cdn/shop/t/26/assets/vendor.min.js?v=114730757745344854631750774549": {
          "crossorigin": null,
          "integrity": null
        },
        "//boutique.marinenationale.gouv.fr/cdn/shop/t/26/assets/theme.js?v=41259982597880492081750774550": {
          "crossorigin": null,
          "integrity": null
        },
        "https://shop.app/checkouts/internal/preloads.js?locale=fr-FR&shop_id=66048983279": {
          "crossorigin": "anonymous",
          "integrity": null
        },
        "//boutique.marinenationale.gouv.fr/cdn/shopifycloud/storefront/assets/storefront/load_feature-81c60534.js": {
          "crossorigin": "anonymous",
          "integrity": "sha256-52AcMU7V7pcBOXWImdc/TAGTFKeNjmkeM1Pvks/DTgc="
        },
        "//boutique.marinenationale.gouv.fr/cdn/shopifycloud/storefront/assets/shopify_pay/storefront-65b4c6d7.js?v=20250812": {
          "crossorigin": "anonymous",
          "integrity": null
        },
        "https://smartarget.online/loader.js?u=aaaeff6d0373aae39628b214622096004ed68998": {
          "crossorigin": null,
          "integrity": null
        }
      }
    },
    "x-content-type-options": {
      "expectation": "x-content-type-options-nosniff",
      "pass": true,
      "result": "x-content-type-options-nosniff",
      "scoreModifier": 0,
      "data": "nosniff"
    },
    "x-frame-options": {
      "expectation": "x-frame-options-sameorigin-or-deny",
      "pass": true,
      "result": "x-frame-options-implemented-via-csp",
      "scoreModifier": 5,
      "data": "DENY"
    },
    "cross-origin-resource-policy": {
      "expectation": "corp-implemented-with-same-site",
      "pass": true,
      "result": "corp-not-implemented",
      "scoreModifier": 0,
      "data": null,
      "http": false,
      "meta": false
    }
  }
}
